{
  "settings": "Settings",
  "dark_mode": "Dark mode",
  "change_language": "Change language",
  "high_contrast_mode": "High contrast mode",
  "how_to_play": "How to play",
  "enter": "enter",
  "wordle": "wordle",
  "auth_fail_message": "Authentication Failure",
  "invalid_email_message": "invalid email",
  "invalid_password_message": "invalid password",
  "login": "Login",
  " create_account": "create account",
  "sign_up_failure": "Sign Up Failure",
  "passwords_no_match": "passwords do not match",
  "sign_up": "sign up",
  "statistic": "Statistic",
  "example_letter": "L",
  "letter_incorrect": "Letter is incorrect",
  "letter_incorrect_spot": "Letter is in incorrect spot",
  "letter_correct": "Letter exists and is in correct spot",
  "confirm_password": "Confirm password",
  "password": "Password",
  "email": "Email",
  "win_message": "You win!",
  "lose_message": "You lost",
  "next_wordle": "Next wordle in",
  "word_not_found": "Word not found in dictionary",
  "word_too_short": "Word is not correct length",
  "app_language": "App language",
  "played": "Played",
  "win_percent": "Win %",
  "current_streak": "Current\nStreak",
  "max_streak": "Max\nStreak",
  "guess_distribution": "Guess Distribution",
  "dictionary_language": "Dictionary language",
  "working_on_improving_dictionaries": "We are working on improving dictionaries\nSoon all words will be with an explanation of the meaning",
  "secret_word_is": "Secret word is \"${word}\"",
  "share": "Share",
  "text_copied": "The text is copied to the clipboard",
  "check_my_result": "Check out my wordle result!\nYou can download game here:\nhttps://github.com/Carapacik/Wordle\n${emoji}"
}